wpa_pyfi/__init__.py
wpa_pyfi/__main__.py
wpa_pyfi/cli.py
wpa_pyfi/exceptions.py
wpa_pyfi/network.py
wpa_pyfi/scan.py
wpa_pyfi/subprocess_compat.py
wpa_pyfi/utils.py
wpa_pyfi-0.5.2.dist-info/LICENSE
wpa_pyfi-0.5.2.dist-info/METADATA
wpa_pyfi-0.5.2.dist-info/WHEEL
wpa_pyfi-0.5.2.dist-info/entry_points.txt
wpa_pyfi-0.5.2.dist-info/top_level.txt
wpa_pyfi-0.5.2.dist-info/RECORD
