Metadata-Version: 2.1
Name: wpa-pyfi
Version: 0.5.2
Summary: Command line tool and library wrapper around '/etc/wpa_supplicant/wpa_supplicant.conf'
Home-page: https://github.com/garretthagen21/wpa_pyfi.git
Author: Garrett Hagen, Rocky Meza, Gavin Wahl
Author-email: garretthagen21@gmail.com
License: BSD
Platform: Debian
Classifier: License :: OSI Approved :: BSD License
Classifier: Topic :: System :: Networking
Classifier: Operating System :: POSIX :: Linux
Classifier: Environment :: Console
Classifier: Programming Language :: Python
Classifier: Programming Language :: Python :: 3.4
Classifier: Programming Language :: Python :: 3.5
Classifier: Programming Language :: Python :: 3.6
Classifier: Programming Language :: Python :: 3.7
Classifier: Programming Language :: Python :: 3.8
Requires-Dist: setuptools
Requires-Dist: ifconfig-parser
